duit_rest/RESTEndpoint.py
duit_rest/RESTRoute.py
duit_rest/RESTService.py
duit_rest/__init__.py
example/SimpleExample.py
example/__init__.py
duit_rest-0.1.0.dist-info/LICENSE
duit_rest-0.1.0.dist-info/METADATA
duit_rest-0.1.0.dist-info/WHEEL
duit_rest-0.1.0.dist-info/top_level.txt
duit_rest-0.1.0.dist-info/RECORD
