Metadata-Version: 2.1
Name: duit-rest
Version: 0.1.0
Summary: A web based REST API for the duit library.
Home-page: https://github.com/cansik/duit-rest
Author: Florian Bruggisser
Author-email: github@broox.ch
License: MIT License
License-File: LICENSE
Requires-Dist: duit~=0.1.12
Requires-Dist: fastapi~=0.110
Requires-Dist: uvicorn[standard]~=0.24
Provides-Extra: all
